[
{
"Rank":233,
"Name":"SaintMartin",
"Density":0,
"Density(mi²)":0
},
{
"Rank":232,
"Name":"Guernsey",
"Density":0,
"Density(mi²)":0
},
{
"Rank":231,
"Name":"Jersey",
"Density":0,
"Density(mi²)":0
},
{
"Rank":230,
"Name":"Greenland",
"Density":0.026113921607914,
"Density(mi²)":0.01008259521541081
},
{
"Rank":229,
"Name":"FalklandIslands",
"Density":0.2400394315287932,
"Density(mi²)":0.09267931719258425
},
{
"Rank":228,
"Name":"Mongolia",
"Density":1.9958775277953598,
"Density(mi²)":0.7706090840908726
},
{
"Rank":227,
"Name":"WesternSahara",
"Density":2.1331616541353378,
"Density(mi²)":0.8236145382761922
},
{
"Rank":226,
"Name":"Namibia",
"Density":3.134391938130969,
"Density(mi²)":1.2101899375023046
},
{
"Rank":225,
"Name":"Australia",
"Density":3.220510882441345,
"Density(mi²)":1.2434404951510984
},
{
"Rank":224,
"Name":"Iceland",
"Density":3.279417475728155,
"Density(mi²)":1.2661843535629944
},
{
"Rank":223,
"Name":"FrenchGuiana",
"Density":3.4688031220820266,
"Density(mi²)":1.3393062247420953
},
{
"Rank":222,
"Name":"Suriname",
"Density":3.4690575021364904,
"Density(mi²)":1.33940444097934
},
{
"Rank":221,
"Name":"Guyana",
"Density":3.638780475324349,
"Density(mi²)":1.4049345464572776
},
{
"Rank":220,
"Name":"Libya",
"Density":3.677640747013424,
"Density(mi²)":1.4199385123603954
},
{
"Rank":219,
"Name":"Canada",
"Density":3.701050209971887,
"Density(mi²)":1.4289769150470606
},
{
"Rank":218,
"Name":"Botswana",
"Density":4.008936426116838,
"Density(mi²)":1.5478519019756132
},
{
"Rank":217,
"Name":"Mauritania",
"Density":4.404839429513922,
"Density(mi²)":1.7007102044455298
},
{
"Rank":216,
"Name":"Niue",
"Density":6.246153846153846,
"Density(mi²)":2.4116424116424118
},
{
"Rank":215,
"Name":"Kazakhstan",
"Density":6.753957943410767,
"Density(mi²)":2.607705769656667
},
{
"Rank":214,
"Name":"CentralAfricanRepublic",
"Density":7.604405570608555,
"Density(mi²)":2.93606392687589
},
{
"Rank":213,
"Name":"Gabon",
"Density":7.724348820180224,
"Density(mi²)":2.9823740618456465
},
{
"Rank":212,
"Name":"Russia",
"Density":8.419854450533569,
"Density(mi²)":3.2509090542600654
},
{
"Rank":211,
"Name":"Bolivia",
"Density":10.209237188700696,
"Density(mi²)":3.9417904203477594
},
{
"Rank":210,
"Name":"Chad",
"Density":11.957308411214953,
"Density(mi²)":4.6167213942914875
},
{
"Rank":209,
"Name":"Turkmenistan",
"Density":11.988252407293585,
"Density(mi²)":4.628668883124936
},
{
"Rank":208,
"Name":"NewCaledonia",
"Density":15.064387617765812,
"Density(mi²)":5.816365875585256
},
{
"Rank":207,
"Name":"Mali",
"Density":15.407054714108787,
"Density(mi²)":5.948669773787176
},
{
"Rank":206,
"Name":"Oman",
"Density":15.605641357027464,
"Density(mi²)":6.025344153292457
},
{
"Rank":205,
"Name":"SaudiArabia",
"Density":15.608921751508356,
"Density(mi²)":6.026610714868092
},
{
"Rank":204,
"Name":"RepublicoftheCongo",
"Density":15.789166666666667,
"Density(mi²)":6.096203346203347
},
{
"Rank":203,
"Name":"Argentina",
"Density":16.07281829952525,
"Density(mi²)":6.20572135116805
},
{
"Rank":202,
"Name":"Finland",
"Density":16.37743481549772,
"Density(mi²)":6.323333905597575
},
{
"Rank":201,
"Name":"Norway",
"Density":16.532828703961062,
"Density(mi²)":6.383331545930912
},
{
"Rank":200,
"Name":"Belize",
"Density":16.652616911956805,
"Density(mi²)":6.429581819288342
},
{
"Rank":199,
"Name":"Paraguay",
"Density":16.956051844858784,
"Density(mi²)":6.546738164038141
},
{
"Rank":198,
"Name":"NewZealand",
"Density":17.5607301445278,
"Density(mi²)":6.780204689006872
},
{
"Rank":197,
"Name":"Niger",
"Density":17.609609313338595,
"Density(mi²)":6.799076954956987
},
{
"Rank":196,
"Name":"Algeria",
"Density":17.63754077374492,
"Density(mi²)":6.809861302604217
},
{
"Rank":195,
"Name":"PapuaNewGuinea",
"Density":18.18845821450177,
"Density(mi²)":7.022570739189874
},
{
"Rank":194,
"Name":"Uruguay",
"Density":19.165189964316095,
"Density(mi²)":7.39968724490969
},
{
"Rank":193,
"Name":"SouthSudan",
"Density":20.845755915739538,
"Density(mi²)":8.048554407621443
},
{
"Rank":192,
"Name":"Bhutan",
"Density":21.28077303745377,
"Density(mi²)":8.216514686275588
},
{
"Rank":191,
"Name":"SolomonIslands",
"Density":21.569802048726466,
"Density(mi²)":8.328108899122189
},
{
"Rank":190,
"Name":"Sudan",
"Density":22.009559570492687,
"Density(mi²)":8.497899448066676
},
{
"Rank":189,
"Name":"Sweden",
"Density":22.169264593211118,
"Density(mi²)":8.559561619000432
},
{
"Rank":188,
"Name":"Vanuatu",
"Density":23.14521289687423,
"Density(mi²)":8.936375635858777
},
{
"Rank":187,
"Name":"Zambia",
"Density":23.397418590189897,
"Density(mi²)":9.03375235142467
},
{
"Rank":186,
"Name":"Somalia",
"Density":23.80892078343059,
"Density(mi²)":9.192633507116058
},
{
"Rank":185,
"Name":"Chile",
"Density":24.067135121980897,
"Density(mi²)":9.292330162926987
},
{
"Rank":184,
"Name":"Angola",
"Density":24.68453116226839,
"Density(mi²)":9.530707012458837
},
{
"Rank":183,
"Name":"Brazil",
"Density":24.762062419039882,
"Density(mi²)":9.56064186063316
},
{
"Rank":182,
"Name":"Peru",
"Density":25.32789429947962,
"Density(mi²)":9.77910976813885
},
{
"Rank":181,
"Name":"SaintPierreandMiquelon",
"Density":26.206611570247937,
"Density(mi²)":10.118382845655574
},
{
"Rank":180,
"Name":"Bahamas",
"Density":28.636950441081545,
"Density(mi²)":11.056737622039208
},
{
"Rank":179,
"Name":"Estonia",
"Density":28.893979260176444,
"Density(mi²)":11.155976548330674
},
{
"Rank":178,
"Name":"Laos",
"Density":29.39700168918919,
"Density(mi²)":11.35019370238965
},
{
"Rank":177,
"Name":"Latvia",
"Density":29.894174321163582,
"Density(mi²)":11.542152247553508
},
{
"Rank":176,
"Name":"Kyrgyzstan",
"Density":30.672174682797284,
"Density(mi²)":11.84253848756652
},
{
"Rank":175,
"Name":"UnitedStates",
"Density":34.8640077843845,
"Density(mi²)":13.461006866557723
},
{
"Rank":174,
"Name":"Venezuela",
"Density":35.333512649422495,
"Density(mi²)":13.642282876224902
},
{
"Rank":173,
"Name":"FaroeIslands",
"Density":35.52692031586504,
"Density(mi²)":13.716957650913145
},
{
"Rank":172,
"Name":"DRCongo",
"Density":35.825192399710346,
"Density(mi²)":13.832120617648783
},
{
"Rank":171,
"Name":"TurksandCaicosIslands",
"Density":37.93565400843882,
"Density(mi²)":14.646970659628888
},
{
"Rank":170,
"Name":"Mozambique",
"Density":38.08514702029716,
"Density(mi²)":14.704689969226703
},
{
"Rank":169,
"Name":"Djibouti",
"Density":41.871034482758624,
"Density(mi²)":16.166422580215684
},
{
"Rank":168,
"Name":"Zimbabwe",
"Density":43.28332185987712,
"Density(mi²)":16.71170728180584
},
{
"Rank":167,
"Name":"Colombia",
"Density":43.32364322074574,
"Density(mi²)":16.727275374805306
},
{
"Rank":166,
"Name":"Liberia",
"Density":43.58049367418222,
"Density(mi²)":16.82644543404719
},
{
"Rank":165,
"Name":"Lithuania",
"Density":44.050153139356816,
"Density(mi²)":17.0077811348868
},
{
"Rank":164,
"Name":"Eritrea",
"Density":44.115204081632655,
"Density(mi²)":17.032897328815697
},
{
"Rank":163,
"Name":"Madagascar",
"Density":44.73760776504537,
"Density(mi²)":17.273207631291648
},
{
"Rank":162,
"Name":"Belarus",
"Density":45.53040944123315,
"Density(mi²)":17.579308664568785
},
{
"Rank":161,
"Name":"Montenegro",
"Density":45.55596582681726,
"Density(mi²)":17.58917599491014
},
{
"Rank":160,
"Name":"EquatorialGuinea",
"Density":46.83947096360201,
"Density(mi²)":18.08473782378456
},
{
"Rank":159,
"Name":"SouthAfrica",
"Density":47.00792932564696,
"Density(mi²)":18.149779662411955
},
{
"Rank":158,
"Name":"Palau",
"Density":47.85185185185186,
"Density(mi²)":18.475618475618482
},
{
"Rank":157,
"Name":"Nicaragua",
"Density":48.20597056138924,
"Density(mi²)":18.612343846096234
},
{
"Rank":156,
"Name":"Iran",
"Density":49.75851461750582,
"Density(mi²)":19.211781705600703
},
{
"Rank":155,
"Name":"Fiji",
"Density":49.92562390542908,
"Density(mi²)":19.276302666188833
},
{
"Rank":154,
"Name":"Montserrat",
"Density":51.00980392156862,
"Density(mi²)":19.694904989022632
},
{
"Rank":153,
"Name":"Cameroon",
"Density":51.905877057559074,
"Density(mi²)":20.040879172802732
},
{
"Rank":152,
"Name":"Guinea-Bissau",
"Density":52.79634602076124,
"Density(mi²)":20.384689583305498
},
{
"Rank":151,
"Name":"Guinea",
"Density":53.09024351553952,
"Density(mi²)":20.49816351951333
},
{
"Rank":150,
"Name":"Yemen",
"Density":54.76711467361658,
"Density(mi²)":21.145604121087484
},
{
"Rank":149,
"Name":"Panama",
"Density":55.19469085219512,
"Density(mi²)":21.310691448723986
},
{
"Rank":148,
"Name":"Afghanistan",
"Density":55.76740720298054,
"Density(mi²)":21.53181745288824
},
{
"Rank":147,
"Name":"Georgia",
"Density":56.056398852223815,
"Density(mi²)":21.643397240240855
},
{
"Rank":146,
"Name":"Ecuador",
"Density":60.91375554921417,
"Density(mi²)":23.51882453637613
},
{
"Rank":145,
"Name":"Tanzania",
"Density":62.52481729195301,
"Density(mi²)":24.14085609727916
},
{
"Rank":144,
"Name":"Bulgaria",
"Density":63.46420873204124,
"Density(mi²)":24.503555494996622
},
{
"Rank":143,
"Name":"Tajikistan",
"Density":63.642285115303984,
"Density(mi²)":24.572310855329725
},
{
"Rank":142,
"Name":"Mexico",
"Density":66.56523016226537,
"Density(mi²)":25.700861066511724
},
{
"Rank":141,
"Name":"Ireland",
"Density":68.35837377086506,
"Density(mi²)":26.393194506125507
},
{
"Rank":140,
"Name":"BosniaandHerzegovina",
"Density":68.41676267843543,
"Density(mi²)":26.415738485882407
},
{
"Rank":139,
"Name":"FrenchPolynesia",
"Density":68.60067194624432,
"Density(mi²)":26.486745925190856
},
{
"Rank":138,
"Name":"Samoa",
"Density":69.56192821956368,
"Density(mi²)":26.857887343460884
},
{
"Rank":137,
"Name":"Tunisia",
"Density":71.26198887598558,
"Density(mi²)":27.514281419299454
},
{
"Rank":136,
"Name":"Uzbekistan",
"Density":72.34017881090746,
"Density(mi²)":27.93057096946234
},
{
"Rank":135,
"Name":"BurkinaFaso",
"Density":72.35911666978059,
"Density(mi²)":27.937882884085173
},
{
"Rank":134,
"Name":"Ukraine",
"Density":72.92330405965204,
"Density(mi²)":28.15571585314751
},
{
"Rank":133,
"Name":"Croatia",
"Density":73.59053963317665,
"Density(mi²)":28.41333576570527
},
{
"Rank":132,
"Name":"CookIslands",
"Density":73.77542372881355,
"Density(mi²)":28.4847195864145
},
{
"Rank":131,
"Name":"Lesotho",
"Density":74.55147422170977,
"Density(mi²)":28.784352981355124
},
{
"Rank":130,
"Name":"Brunei",
"Density":75.29505637467476,
"Density(mi²)":29.071450337712264
},
{
"Rank":129,
"Name":"IvoryCoast",
"Density":77.23628137181629,
"Density(mi²)":29.82095805861633
},
{
"Rank":128,
"Name":"Myanmar",
"Density":79.60018652690451,
"Density(mi²)":30.733662751700585
},
{
"Rank":127,
"Name":"Swaziland",
"Density":80.13044229440221,
"Density(mi²)":30.938394708263406
},
{
"Rank":126,
"Name":"Morocco",
"Density":81.04759825327511,
"Density(mi²)":31.2925089780985
},
{
"Rank":125,
"Name":"Macedonia",
"Density":81.08937113522343,
"Density(mi²)":31.30863750394727
},
{
"Rank":124,
"Name":"Romania",
"Density":82.13663267489125,
"Density(mi²)":31.7129855887611
},
{
"Rank":123,
"Name":"WallisandFutuna",
"Density":82.27464788732394,
"Density(mi²)":31.76627331556909
},
{
"Rank":122,
"Name":"Senegal",
"Density":82.82891593212757,
"Density(mi²)":31.98027642167088
},
{
"Rank":121,
"Name":"Honduras",
"Density":83.71410411407034,
"Density(mi²)":32.322047920490476
},
{
"Rank":120,
"Name":"Greece",
"Density":84.41670581104628,
"Density(mi²)":32.593322706967676
},
{
"Rank":119,
"Name":"Kenya",
"Density":87.79079272253591,
"Density(mi²)":33.896058966230086
},
{
"Rank":118,
"Name":"Timor-Leste",
"Density":89.02070727443862,
"Density(mi²)":34.3709294495902
},
{
"Rank":117,
"Name":"Cambodia",
"Density":89.73805617698235,
"Density(mi²)":34.64789813783103
},
{
"Rank":116,
"Name":"Iraq",
"Density":89.75183029633804,
"Density(mi²)":34.65321633063245
},
{
"Rank":115,
"Name":"Spain",
"Density":91.69601890938989,
"Density(mi²)":35.40386830478374
},
{
"Rank":114,
"Name":"Malaysia",
"Density":96.8626584402197,
"Density(mi²)":37.39870982247865
},
{
"Rank":113,
"Name":"CostaRica",
"Density":96.93148727984347,
"Density(mi²)":37.425284664032226
},
{
"Rank":112,
"Name":"Ethiopia",
"Density":97.37832291949651,
"Density(mi²)":37.59780807702568
},
{
"Rank":111,
"Name":"Armenia",
"Density":98.65016978784924,
"Density(mi²)":38.088868643957234
},
{
"Rank":110,
"Name":"Syria",
"Density":98.73856247974943,
"Density(mi²)":38.12299709642836
},
{
"Rank":109,
"Name":"Dominica",
"Density":98.94540612516644,
"Density(mi²)":38.20285950778627
},
{
"Rank":108,
"Name":"Egypt",
"Density":99.13286547957505,
"Density(mi²)":38.275237636901565
},
{
"Rank":107,
"Name":"Serbia",
"Density":99.16170029764262,
"Density(mi²)":38.28637077129059
},
{
"Rank":106,
"Name":"Benin",
"Density":101.98428371010992,
"Density(mi²)":39.37617131664476
},
{
"Rank":105,
"Name":"Albania",
"Density":102.07190065395854,
"Density(mi²)":39.410000252493646
},
{
"Rank":104,
"Name":"Slovenia",
"Density":102.66166822867855,
"Density(mi²)":39.63770974080253
},
{
"Rank":103,
"Name":"Hungary",
"Density":104.14979361052586,
"Density(mi²)":40.21227552529956
},
{
"Rank":102,
"Name":"Austria",
"Density":104.34858294285272,
"Density(mi²)":40.2890281632636
},
{
"Rank":101,
"Name":"Turkey",
"Density":104.54421092396007,
"Density(mi²)":40.364560202301185
},
{
"Rank":100,
"Name":"Cuba",
"Density":104.55645953915038,
"Density(mi²)":40.36928939735536
},
{
"Rank":99,
"Name":"SierraLeone",
"Density":107.60703930861445,
"Density(mi²)":41.54711942417546
},
{
"Rank":98,
"Name":"Tokelau",
"Density":109.91666666666667,
"Density(mi²)":42.43886743886744
},
{
"Rank":97,
"Name":"Jordan",
"Density":110.8527008573795,
"Density(mi²)":42.80027060130483
},
{
"Rank":96,
"Name":"Slovakia",
"Density":111.13681505801742,
"Density(mi²)":42.90996720386773
},
{
"Rank":95,
"Name":"Portugal",
"Density":111.75150396351395,
"Density(mi²)":43.147298827611564
},
{
"Rank":94,
"Name":"UnitedArabEmirates",
"Density":114.13415071770335,
"Density(mi²)":44.06723965934493
},
{
"Rank":93,
"Name":"Azerbaijan",
"Density":114.59484988452655,
"Density(mi²)":44.24511578553149
},
{
"Rank":92,
"Name":"France",
"Density":118.24154831927059,
"Density(mi²)":45.65310745917784
},
{
"Rank":91,
"Name":"NorthernMarianaIslands",
"Density":118.95258620689654,
"Density(mi²)":45.92763946212222
},
{
"Rank":90,
"Name":"Moldova",
"Density":119.39564498020445,
"Density(mi²)":46.09870462556157
},
{
"Rank":89,
"Name":"Poland",
"Density":121.8656577512401,
"Density(mi²)":47.052377510131315
},
{
"Rank":88,
"Name":"Ghana",
"Density":123.5201963669597,
"Density(mi²)":47.69119550847865
},
{
"Rank":87,
"Name":"Cyprus",
"Density":128.53583396389578,
"Density(mi²)":49.627735121195286
},
{
"Rank":86,
"Name":"Denmark",
"Density":133.53032904812736,
"Density(mi²)":51.55611160159358
},
{
"Rank":85,
"Name":"CzechRepublic",
"Density":134.72706523806505,
"Density(mi²)":52.018171906588826
},
{
"Rank":84,
"Name":"Thailand",
"Density":134.8284475366386,
"Density(mi²)":52.05731565121182
},
{
"Rank":83,
"Name":"CapeVerde",
"Density":137.2018348623853,
"Density(mi²)":52.973681414048386
},
{
"Rank":82,
"Name":"Indonesia",
"Density":140.08155125910375,
"Density(mi²)":54.085541026680986
},
{
"Rank":81,
"Name":"Togo",
"Density":140.72247952804437,
"Density(mi²)":54.333003678781616
},
{
"Rank":80,
"Name":"China",
"Density":145.77641014525557,
"Density(mi²)":56.28432824141142
},
{
"Rank":79,
"Name":"Tonga",
"Density":145.9277108433735,
"Density(mi²)":56.34274549937201
},
{
"Rank":78,
"Name":"Kiribati",
"Density":146.0098643649815,
"Density(mi²)":56.374465005784366
},
{
"Rank":77,
"Name":"IsleofMan",
"Density":148.30594405594405,
"Density(mi²)":57.26098226098226
},
{
"Rank":76,
"Name":"Micronesia",
"Density":151.32051282051282,
"Density(mi²)":58.42490842490843
},
{
"Rank":75,
"Name":"Guatemala",
"Density":158.37546492299498,
"Density(mi²)":61.14882815559652
},
{
"Rank":74,
"Name":"Malawi",
"Density":161.74950204246986,
"Density(mi²)":62.4515451901428
},
{
"Rank":73,
"Name":"Andorra",
"Density":164.42948717948718,
"Density(mi²)":63.486288486288494
},
{
"Rank":72,
"Name":"Anguilla",
"Density":165.32967032967034,
"Density(mi²)":63.83384954813527
},
{
"Rank":71,
"Name":"Uganda",
"Density":183.2770151107431,
"Density(mi²)":70.76332629758421
},
{
"Rank":70,
"Name":"Italy",
"Density":196.76032402368122,
"Density(mi²)":75.9692370747804
},
{
"Rank":69,
"Name":"Nepal",
"Density":201.27621771831963,
"Density(mi²)":77.71282537386858
},
{
"Rank":68,
"Name":"Gambia",
"Density":202.42913275329778,
"Density(mi²)":78.15796631401459
},
{
"Rank":67,
"Name":"Switzerland",
"Density":206.95751380680167,
"Density(mi²)":79.90637598718212
},
{
"Rank":66,
"Name":"BritishVirginIslands",
"Density":210.05960264900662,
"Density(mi²)":81.10409368687515
},
{
"Rank":65,
"Name":"Seychelles",
"Density":210.69690265486724,
"Density(mi²)":81.35015546519972
},
{
"Rank":64,
"Name":"Nigeria",
"Density":212.0394265659776,
"Density(mi²)":81.86850446562842
},
{
"Rank":63,
"Name":"NorthKorea",
"Density":212.46969420431734,
"Density(mi²)":82.03463096691789
},
{
"Rank":62,
"Name":"SaintKittsandNevis",
"Density":213.98467432950193,
"Density(mi²)":82.61956537818608
},
{
"Rank":61,
"Name":"SaoTomeandPrincipe",
"Density":216.61618257261406,
"Density(mi²)":83.63559172687802
},
{
"Rank":60,
"Name":"DominicanRepublic",
"Density":223.60329559696743,
"Density(mi²)":86.33331876330789
},
{
"Rank":59,
"Name":"Pakistan",
"Density":227.70278440479322,
"Density(mi²)":87.91613297482364
},
{
"Rank":58,
"Name":"Luxembourg",
"Density":228.27571539056459,
"Density(mi²)":88.13734184963884
},
{
"Rank":57,
"Name":"Germany",
"Density":230.44029917617343,
"Density(mi²)":88.97308848500904
},
{
"Rank":56,
"Name":"Qatar",
"Density":232.5952874158467,
"Density(mi²)":89.8051302763887
},
{
"Rank":55,
"Name":"AntiguaandBarbuda",
"Density":233.1447963800905,
"Density(mi²)":90.01729589964884
},
{
"Rank":54,
"Name":"Kuwait",
"Density":235.55550566842518,
"Density(mi²)":90.94807168665065
},
{
"Rank":53,
"Name":"CaymanIslands",
"Density":236.16666666666666,
"Density(mi²)":91.18404118404119
},
{
"Rank":52,
"Name":"Liechtenstein",
"Density":238.46875,
"Density(mi²)":92.07287644787645
},
{
"Rank":51,
"Name":"Jamaica",
"Density":263.73187153125286,
"Density(mi²)":101.82697742519416
},
{
"Rank":50,
"Name":"TrinidadandTobago",
"Density":267.56296296296296,
"Density(mi²)":103.30616330616331
},
{
"Rank":49,
"Name":"UnitedKingdom",
"Density":274.0778262659531,
"Density(mi²)":105.82155454283904
},
{
"Rank":48,
"Name":"Guadeloupe",
"Density":275.90479115479116,
"Density(mi²)":106.52694639181126
},
{
"Rank":47,
"Name":"AmericanSamoa",
"Density":279.7939698492462,
"Density(mi²)":108.02855978735374
},
{
"Rank":46,
"Name":"SaintVincentandtheGrenadines",
"Density":283.2904884318766,
"Density(mi²)":109.37856696211453
},
{
"Rank":45,
"Name":"Vietnam",
"Density":291.32744586548796,
"Density(mi²)":112.48163933030423
},
{
"Rank":44,
"Name":"SaintLucia",
"Density":291.6672077922078,
"Density(mi²)":112.61282154139299
},
{
"Rank":43,
"Name":"MarshallIslands",
"Density":293.7403314917127,
"Density(mi²)":113.41325540220569
},
{
"Rank":42,
"Name":"Guam",
"Density":301.8542805100182,
"Density(mi²)":116.54605425097229
},
{
"Rank":41,
"Name":"UnitedStatesVirginIslands",
"Density":302.3458213256484,
"Density(mi²)":116.7358383496712
},
{
"Rank":40,
"Name":"ElSalvador",
"Density":304.7173613421416,
"Density(mi²)":117.65149086569174
},
{
"Rank":39,
"Name":"Philippines",
"Density":311.1176884677512,
"Density(mi²)":120.12265964005837
},
{
"Rank":38,
"Name":"Grenada",
"Density":314.9389534883721,
"Density(mi²)":121.598051539912
},
{
"Rank":37,
"Name":"SriLanka",
"Density":319.31170553269317,
"Density(mi²)":123.28637279254563
},
{
"Rank":36,
"Name":"Japan",
"Density":336.5314529145609,
"Density(mi²)":129.93492390523588
},
{
"Rank":35,
"Name":"Martinique",
"Density":341.36968085106383,
"Density(mi²)":131.80296557956135
},
{
"Rank":34,
"Name":"Reunion",
"Density":351.7510951812027,
"Density(mi²)":135.81123366069602
},
{
"Rank":33,
"Name":"Curacao",
"Density":363.9121621621622,
"Density(mi²)":140.50662631743714
},
{
"Rank":32,
"Name":"Belgium",
"Density":376.654841457023,
"Density(mi²)":145.4265797131363
},
{
"Rank":31,
"Name":"Haiti",
"Density":400.4664864864865,
"Density(mi²)":154.62026505269748
},
{
"Rank":30,
"Name":"Burundi",
"Density":402.9765754113674,
"Density(mi²)":155.5894113557403
},
{
"Rank":29,
"Name":"Israel",
"Density":406.97356764564273,
"Density(mi²)":157.13265160063426
},
{
"Rank":28,
"Name":"Netherlands",
"Density":408.2308004778973,
"Density(mi²)":157.61806968258583
},
{
"Rank":27,
"Name":"India",
"Density":411.86761548733267,
"Density(mi²)":159.0222453619045
},
{
"Rank":26,
"Name":"PuertoRico",
"Density":412.5148816234498,
"Density(mi²)":159.27215506696905
},
{
"Rank":25,
"Name":"Tuvalu",
"Density":434.11538461538464,
"Density(mi²)":167.61211761211763
},
{
"Rank":24,
"Name":"Comoros",
"Density":447.01772287862514,
"Density(mi²)":172.59371539715258
},
{
"Rank":23,
"Name":"Rwanda",
"Density":474.64332903029845,
"Density(mi²)":183.25997259857084
},
{
"Rank":22,
"Name":"SouthKorea",
"Density":510.57214848817483,
"Density(mi²)":197.13210366338797
},
{
"Rank":21,
"Name":"Nauru",
"Density":538.6666666666667,
"Density(mi²)":207.97940797940802
},
{
"Rank":20,
"Name":"SanMarino",
"Density":550.1147540983605,
"Density(mi²)":212.39951895689597
},
{
"Rank":19,
"Name":"Lebanon",
"Density":582.9993302717183,
"Density(mi²)":225.096266514177
},
{
"Rank":18,
"Name":"Aruba",
"Density":587.0555555555555,
"Density(mi²)":226.66237666237666
},
{
"Rank":17,
"Name":"Mauritius",
"Density":621.7230392156863,
"Density(mi²)":240.047505488682
},
{
"Rank":16,
"Name":"Taiwan",
"Density":654.6594369076894,
"Density(mi²)":252.76426135432024
},
{
"Rank":15,
"Name":"Barbados",
"Density":666.0186046511628,
"Density(mi²)":257.1500404058544
},
{
"Rank":14,
"Name":"Mayotte",
"Density":694.336898395722,
"Density(mi²)":268.08374455433284
},
{
"Rank":13,
"Name":"Palestine",
"Density":812.3434083601286,
"Density(mi²)":313.64610361394926
},
{
"Rank":12,
"Name":"Bangladesh",
"Density":1127.3846242461204,
"Density(mi²)":435.2836387050658
},
{
"Rank":11,
"Name":"Bermuda",
"Density":1130.9259259259259,
"Density(mi²)":436.65093665093667
},
{
"Rank":10,
"Name":"SintMaarten",
"Density":1192.7058823529412,
"Density(mi²)":460.5042016806723
},
{
"Rank":9,
"Name":"Malta",
"Density":1367.370253164557,
"Density(mi²)":527.9421826890182
},
{
"Rank":8,
"Name":"Maldives",
"Density":1480.8633333333332,
"Density(mi²)":571.7619047619047
},
{
"Rank":7,
"Name":"VaticanCity",
"Density":1820.4545454545453,
"Density(mi²)":702.8782028782028
},
{
"Rank":6,
"Name":"Bahrain",
"Density":2048.356862745098,
"Density(mi²)":790.871375577258
},
{
"Rank":5,
"Name":"Gibraltar",
"Density":5788.833333333335,
"Density(mi²)":2235.070785070786
},
{
"Rank":4,
"Name":"HongKong",
"Density":6729.064311594203,
"Density(mi²)":2598.0943288008507
},
{
"Rank":3,
"Name":"Singapore",
"Density":8157.607042253521,
"Density(mi²)":3149.6552286693136
},
{
"Rank":2,
"Name":"Monaco",
"Density":19255.940594059404,
"Density(mi²)":7434.726098092435
},
{
"Rank":1,
"Name":"Macau",
"Density":21080.6,
"Density(mi²)":8139.2277992278
}
]